agent/__init__.py
metricrule/agent/__init__.py
metricrule/agent/asgi.py
metricrule/agent/mrconfig.py
metricrule/agent/mrmetric.py
metricrule/agent/mrotel.py
metricrule/agent/mrrecorder.py
metricrule/agent/wsgi.py
metricrule/config_gen/__init__.py
metricrule/config_gen/metric_configuration_pb2.py
metricrule-0.0.1.dist-info/LICENSE
metricrule-0.0.1.dist-info/METADATA
metricrule-0.0.1.dist-info/WHEEL
metricrule-0.0.1.dist-info/top_level.txt
metricrule-0.0.1.dist-info/RECORD
