Metadata-Version: 2.1
Name: metricrule
Version: 0.0.1
Summary: MetricRule agent for exporting ML serving telemetry
Home-page: https://github.com/metricrule/metricrule-python-agent/tree/main/
Author: MetricRule
Author-email: jishnu@metricrule.com
License: Apache-2.0
Platform: any
Classifier: Development Status :: 3 - Alpha
Classifier: Intended Audience :: Developers
Classifier: License :: OSI Approved :: Apache Software License
Classifier: Programming Language :: Python
Classifier: Programming Language :: Python :: 3
Classifier: Programming Language :: Python :: 3.9
Requires-Python: >=3.9
License-File: LICENSE
Requires-Dist: jsonpath-ng
Requires-Dist: prometheus-client
Requires-Dist: protobuf
Requires-Dist: starlette
Requires-Dist: werkzeug
